[{"name":"Hisuian Growlithe","tier":"Tier 1","canBeShiny":true,"types":[{"name":"fire","image":"https://leekduck.com/assets/img/types/fire.png"},{"name":"rock","image":"https://leekduck.com/assets/img/types/rock.png"}],"combatPower":{"normal":{"min":703,"max":755},"boosted":{"min":879,"max":944}},"boostedWeather":[{"name":"sunnyclear","image":"https://leekduck.com/assets/img/weather/sunny.png"},{"name":"partly","image":"https://leekduck.com/assets/img/weather/partlycloudy.png"}],"image":"https://cdn.leekduck.com/assets/img/pokemon_icons/pm58.fHISUIAN.icon.png"},{"name":"Unown U","tier":"Tier 1","canBeShiny":true,"types":[{"name":"psychic","image":"https://leekduck.com/assets/img/types/psychic.png"}],"combatPower":{"normal":{"min":628,"max":677},"boosted":{"min":785,"max":846}},"boostedWeather":[{"name":"windy","image":"https://leekduck.com/assets/img/weather/windy.png"}],"image":"https://cdn.leekduck.com/assets/img/pokemon_icons/pm201.fUNOWN_U.icon.png"},{"name":"Hisuian Sneasel","tier":"Tier 1","canBeShiny":true,"types":[{"name":"fighting","image":"https://leekduck.com/assets/img/types/fighting.png"},{"name":"poison","image":"https://leekduck.com/assets/img/types/poison.png"}],"combatPower":{"normal":{"min":1107,"max":1172},"boosted":{"min":1384,"max":1465}},"boostedWeather":[{"name":"cloudy","image":"https://leekduck.com/assets/img/weather/cloudy.png"}],"image":"https://cdn.leekduck.com/assets/img/pokemon_icons/pm215.fHISUIAN.icon.png"},{"name":"Hisuian Braviary","tier":"Tier 3","canBeShiny":true,"types":[{"name":"psychic","image":"https://leekduck.com/assets/img/types/psychic.png"},{"name":"flying","image":"https://leekduck.com/assets/img/types/flying.png"}],"combatPower":{"normal":{"min":1531,"max":1608},"boosted":{"min":1914,"max":2010}},"boostedWeather":[{"name":"windy","image":"https://leekduck.com/assets/img/weather/windy.png"}],"image":"https://cdn.leekduck.com/assets/img/pokemon_icons/pm628.fHISUIAN.icon.png"},{"name":"Hisuian Avalugg","tier":"Tier 3","canBeShiny":true,"types":[{"name":"ice","image":"https://leekduck.com/assets/img/types/ice.png"},{"name":"rock","image":"https://leekduck.com/assets/img/types/rock.png"}],"combatPower":{"normal":{"min":1892,"max":1975},"boosted":{"min":2365,"max":2469}},"boostedWeather":[{"name":"snow","image":"https://leekduck.com/assets/img/weather/snowy.png"},{"name":"partly","image":"https://leekduck.com/assets/img/weather/partlycloudy.png"}],"image":"https://cdn.leekduck.com/assets/img/pokemon_icons/pm713.fHISUIAN.icon.png"},{"name":"Wyrdeer","tier":"Tier 3","canBeShiny":true,"types":[{"name":"normal","image":"https://leekduck.com/assets/img/types/normal.png"},{"name":"psychic","image":"https://leekduck.com/assets/img/types/psychic.png"}],"combatPower":{"normal":{"min":1486,"max":1561},"boosted":{"min":1858,"max":1952}},"boostedWeather":[{"name":"partly","image":"https://leekduck.com/assets/img/weather/partlycloudy.png"},{"name":"windy","image":"https://leekduck.com/assets/img/weather/windy.png"}],"image":"https://cdn.leekduck.com/assets/img/pokemon_icons/pm899.icon.png"},{"name":"Kleavor","tier":"Tier 3","canBeShiny":true,"types":[{"name":"bug","image":"https://leekduck.com/assets/img/types/bug.png"},{"name":"rock","image":"https://leekduck.com/assets/img/types/rock.png"}],"combatPower":{"normal":{"min":1717,"max":1798},"boosted":{"min":2147,"max":2247}},"boostedWeather":[{"name":"rainy","image":"https://leekduck.com/assets/img/weather/rainy.png"},{"name":"partly","image":"https://leekduck.com/assets/img/weather/partlycloudy.png"}],"image":"https://cdn.leekduck.com/assets/img/pokemon_icons/pm900.icon.png"},{"name":"Solgaleo","tier":"Tier 5","canBeShiny":false,"types":[{"name":"psychic","image":"https://leekduck.com/assets/img/types/psychic.png"},{"name":"steel","image":"https://leekduck.com/assets/img/types/steel.png"}],"combatPower":{"normal":{"min":2219,"max":2310},"boosted":{"min":2774,"max":2887}},"boostedWeather":[{"name":"windy","image":"https://leekduck.com/assets/img/weather/windy.png"},{"name":"snow","image":"https://leekduck.com/assets/img/weather/snowy.png"}],"image":"https://cdn.leekduck.com/assets/img/pokemon_icons/pm791.icon.png"},{"name":"Mega Charizard X","tier":"Mega","canBeShiny":true,"types":[{"name":"fire","image":"https://leekduck.com/assets/img/types/fire.png"},{"name":"dragon","image":"https://leekduck.com/assets/img/types/dragon.png"}],"combatPower":{"normal":{"min":1574,"max":1651},"boosted":{"min":1968,"max":2064}},"boostedWeather":[{"name":"sunnyclear","image":"https://leekduck.com/assets/img/weather/sunny.png"},{"name":"windy","image":"https://leekduck.com/assets/img/weather/windy.png"}],"image":"https://cdn.leekduck.com/assets/img/pokemon_icons/pokemon_icon_006_51.png"},{"name":"Magnemite","tier":"Shadow Tier 1","canBeShiny":true,"types":[{"name":"electric","image":"https://leekduck.com/assets/img/types/electric.png"},{"name":"steel","image":"https://leekduck.com/assets/img/types/steel.png"}],"combatPower":{"normal":{"min":-1,"max":-1},"boosted":{"min":-1,"max":-1}},"boostedWeather":[],"image":"https://cdn.leekduck.com/assets/img/pokemon_icons/pm81.icon.png"},{"name":"Cyndaquil","tier":"Shadow Tier 1","canBeShiny":false,"types":[{"name":"fire","image":"https://leekduck.com/assets/img/types/fire.png"}],"combatPower":{"normal":{"min":-1,"max":-1},"boosted":{"min":-1,"max":-1}},"boostedWeather":[],"image":"https://cdn.leekduck.com/assets/img/pokemon_icons/pm155.icon.png"},{"name":"Murkrow","tier":"Shadow Tier 1","canBeShiny":true,"types":[{"name":"dark","image":"https://leekduck.com/assets/img/types/dark.png"},{"name":"flying","image":"https://leekduck.com/assets/img/types/flying.png"}],"combatPower":{"normal":{"min":-1,"max":-1},"boosted":{"min":-1,"max":-1}},"boostedWeather":[],"image":"https://cdn.leekduck.com/assets/img/pokemon_icons/pm198.icon.png"},{"name":"Spoink","tier":"Shadow Tier 1","canBeShiny":false,"types":[{"name":"psychic","image":"https://leekduck.com/assets/img/types/psychic.png"}],"combatPower":{"normal":{"min":-1,"max":-1},"boosted":{"min":-1,"max":-1}},"boostedWeather":[],"image":"https://cdn.leekduck.com/assets/img/pokemon_icons/pm325.icon.png"},{"name":"Lapras","tier":"Shadow Tier 3","canBeShiny":false,"types":[{"name":"water","image":"https://leekduck.com/assets/img/types/water.png"},{"name":"ice","image":"https://leekduck.com/assets/img/types/ice.png"}],"combatPower":{"normal":{"min":-1,"max":-1},"boosted":{"min":-1,"max":-1}},"boostedWeather":[],"image":"https://cdn.leekduck.com/assets/img/pokemon_icons/pm131.icon.png"},{"name":"Piloswine","tier":"Shadow Tier 3","canBeShiny":false,"types":[{"name":"ice","image":"https://leekduck.com/assets/img/types/ice.png"},{"name":"ground","image":"https://leekduck.com/assets/img/types/ground.png"}],"combatPower":{"normal":{"min":-1,"max":-1},"boosted":{"min":-1,"max":-1}},"boostedWeather":[],"image":"https://cdn.leekduck.com/assets/img/pokemon_icons/pm221.icon.png"},{"name":"Gurdurr","tier":"Shadow Tier 3","canBeShiny":false,"types":[{"name":"fighting","image":"https://leekduck.com/assets/img/types/fighting.png"}],"combatPower":{"normal":{"min":-1,"max":-1},"boosted":{"min":-1,"max":-1}},"boostedWeather":[],"image":"https://cdn.leekduck.com/assets/img/pokemon_icons/pm533.icon.png"},{"name":"Registeel","tier":"Shadow Tier 5","canBeShiny":false,"types":[{"name":"steel","image":"https://leekduck.com/assets/img/types/steel.png"}],"combatPower":{"normal":{"min":-1,"max":-1},"boosted":{"min":-1,"max":-1}},"boostedWeather":[],"image":"https://cdn.leekduck.com/assets/img/pokemon_icons/pm379.icon.png"}]